xy_health_measurement_sdk/Measurement.py
xy_health_measurement_sdk/MeasurerProcess.py
xy_health_measurement_sdk/Rpcer.py
xy_health_measurement_sdk/__init__.py
xy_health_measurement_sdk/resources/__init__.py
xy_health_measurement_sdk/resources/face_landmarker.task
xy_health_measurement_sdk/resources/libmeasurement.so
xy_health_measurement_sdk/resources/__pycache__/__init__.cpython-310.pyc
xy_health_measurement_sdk/utilities/FeatureExtractor.py
xy_health_measurement_sdk/utilities/SignalProcessor.py
xy_health_measurement_sdk/utilities/Utility.py
xy_health_measurement_sdk/utilities/__init__.py
xy_health_measurement_sdk-2.2.4.dist-info/METADATA
xy_health_measurement_sdk-2.2.4.dist-info/WHEEL
xy_health_measurement_sdk-2.2.4.dist-info/top_level.txt
xy_health_measurement_sdk-2.2.4.dist-info/RECORD
