Metadata-Version: 2.4
Name: xy_health_measurement_sdk
Version: 2.2.4
Summary: 小阳心健康测量SDK
Author-email: Colin Chang <zhangcheng@xymind.cn>
Keywords: 健康测量,生理测量,情绪测量,健康风险,小阳科技
Classifier: Programming Language :: Python :: 3.8
Classifier: Programming Language :: Python :: 3.9
Classifier: Programming Language :: Python :: 3.10
Classifier: Programming Language :: Python :: 3.11
Classifier: License :: OSI Approved :: MIT License
Classifier: Operating System :: OS Independent
Requires-Python: <=3.11,>=3.8
Requires-Dist: blinker==1.7.0
Requires-Dist: numpy==1.26.4
Requires-Dist: opencv-python-headless==4.9.0.80
Requires-Dist: mediapipe==0.10.11
Requires-Dist: xy-health-measurement-sdk-configuration==1.0.2
Requires-Dist: xy-signalrcore==1.0.1
